{"title":"2025-12-27","virtualPath":"/Diary/","anchorId":"1ZVai7z4Ae","anchorLink":"/Gitwee/timeline/2025/12/27","description":"\u65e5\u8a18,\u3064\u3076\u3084\u304d,\u96d1\u8a18\u5e33,\u30e2\u30f3\u30cf\u30f3Now","tags":[{"title":"\u30e2\u30f3\u30cf\u30f3Now","tagkey":"Ga9v46pU3Ch7xz2sKLEMdA","link":"/Gitwee/tag/Ga9v46pU3Ch7xz2sKLEMdA"}],"html":"<div class=\"markdown-body\"><p>\u5384\u4ecb\u306a\u306e\u306f\u30af\u30ea\u30a2\uff01\u3068\u308a\u3042\u3048\u305a\u30b9\u30c8\u30fc\u30ea\u30fc\u306f\u5148\u306b\u9032\u3081\u3066\u3001\u7df4\u7fd2\u306f\u307e\u305f\u5f8c\u3067\u3002</p>\n\n<p><a target=\"_blank\" rel=\"noopener noreferrer\" href=\"/MyContents2025/2025-12-27/1ZVai7z4AeesVOi9/a800d9de9e0bb250c6776fc42a92d21a.jpg\"><img src=\"/MyContents2025/2025-12-27/1ZVai7z4AeesVOi9/a800d9de9e0bb250c6776fc42a92d21a.jpg\" alt=\"\" style=\"max-width: 100%;\"></a></p>\n</div>","styles":["/css/github-markdown.css","/css/markdown-include.css"],"updated":"2025-12-27T04:54:42","published":"2025-12-27T04:54:42","updatedAt":"2025-12-26T19:54:42.00Z","publishedAt":"2025-12-26T19:54:42.00Z"}