{"title":"2020-04-09","virtualPath":"/Diary/","html":"<p>今日もパス消化できず。井上の荘、通りからちょっと離れた東屋も成立せんのね… 田舎ポケモン勢、歩かなさすぎやろ。</p>\n<hr>\n<p>相棒ポケモン名での会話だけだと厳しいね… 何度も言われてるけど NIA の方で軽い SNS 準備するべきだと思うぜ。たぶん、その内大荒れに荒れはじめるだろうし、出会い系的な使い方もされはじめるだろうけど。</p>\n<hr>\n<p>\n<iframe  src=\"https://www.youtube.com/embed/Ad8-7E8PRR0\" frameborder=\"0\" allow=\"accelerometer; autoplay; encrypted-media; gyroscope; picture-in-picture\" allowfullscreen></iframe>\n</p>\n<p>たまたま目にしたんだけど、こういう別々の漫画のキャラで戦うゲームて流行ってんだろうか。ワンピースとドラゴンボール、ブリーチのキャラとかw</p>\n<p>この 20 年ぐらい前の人気キャラがこんな前面に出てくるてことは、新しい人気漫画出てきてないのかな？</p>\n","styles":["/css/github-markdown.css","/css/markdown-include.css"],"description":"日記","updated":"2020-06-30T18:53:18","published":"2020-06-30T18:53:18"}