[{"pokemonId":"COBALION","modelScale":1.26,"type":"POKEMON_TYPE_STEEL","type2":"POKEMON_TYPE_FIGHTING","camera":{"diskRadiusM":0.378,"cylinderRadiusM":1.22,"cylinderHeightM":2.56,"shoulderModeScale":0.5},"encounter":{"baseCaptureRate":0.02,"baseFleeRate":0.01,"collisionRadiusM":0.5,"collisionHeightM":0.1,"collisionHeadRadiusM":0.31,"movementType":"MOVEMENT_JUMP","movementTimerS":10,"jumpTimeS":1.1,"attackTimerS":29,"attackProbability":0.1,"dodgeProbability":0.15,"dodgeDurationS":1,"dodgeDistance":1,"cameraDistance":7,"minPokemonActionFrequencyS":0.2,"maxPokemonActionFrequencyS":1.6,"bonusXlCandyCaptureReward":3},"stats":{"baseStamina":209,"baseAttack":192,"baseDefense":229},"quickMoves":["METAL_CLAW_FAST","ZEN_HEADBUTT_FAST"],"cinematicMoves":["CLOSE_COMBAT","IRON_HEAD","STONE_EDGE"],"animationTime":[1.9,0.6667,1.8,1.7667,0,2.4,0.8667,0],"evolutionPips":1,"pokemonClass":"POKEMON_CLASS_LEGENDARY","pokedexHeightM":2.1,"pokedexWeightKg":250,"heightStdDev":0.2625,"weightStdDev":31.25,"familyId":"FAMILY_COBALION","candyToEvolve":25,"kmBuddyDistance":20,"buddySize":"BUDDY_BIG","modelHeight":2.1,"modelScaleV2":0.99,"buddyOffsetMale":[35,0,0],"buddyOffsetFemale":[35,0,0],"buddyScale":18,"buddyPortraitOffset":[0,0,0],"thirdMove":{"stardustToUnlock":100000,"candyToUnlock":100},"isTransferable":true,"isTradable":true,"buddyGroupNumber":3,"eliteCinematicMove":["SACRED_SWORD"]}]