[{"pokemonId":"DRIFLOON","modelScale":1.26,"type":"POKEMON_TYPE_GHOST","type2":"POKEMON_TYPE_FLYING","camera":{"diskRadiusM":0.378,"cylinderRadiusM":0.75,"cylinderHeightM":0.5,"cylinderGroundM":0.6,"shoulderModeScale":0.5},"encounter":{"baseCaptureRate":0.4,"baseFleeRate":0.1,"collisionRadiusM":0.145,"collisionHeightM":0.252,"collisionHeadRadiusM":0.145,"movementType":"MOVEMENT_FLYING","movementTimerS":10,"jumpTimeS":0.9,"attackTimerS":29,"attackProbability":0.05,"dodgeProbability":0.3,"dodgeDurationS":4,"dodgeDistance":1,"cameraDistance":3,"minPokemonActionFrequencyS":0.2,"maxPokemonActionFrequencyS":1.6},"stats":{"baseStamina":207,"baseAttack":117,"baseDefense":80},"quickMoves":["HEX_FAST","ASTONISH_FAST"],"cinematicMoves":["OMINOUS_WIND","ICY_WIND","SHADOW_BALL"],"animationTime":[1.9,0.6667,1.8,1.7667,0,2.4,0.8667,0],"evolutionPips":1,"pokedexHeightM":0.4,"pokedexWeightKg":1.2,"heightStdDev":0.05,"weightStdDev":0.15,"familyId":"FAMILY_DRIFLOON","candyToEvolve":25,"kmBuddyDistance":5,"modelHeight":0.76,"evolutionBranch":[{"evolution":"DRIFBLIM","candyCost":50}],"modelScaleV2":1,"buddyOffsetMale":[3.3,9.2,6.7],"buddyOffsetFemale":[3.3,9.2,6.7],"buddyScale":19,"buddyPortraitOffset":[0.63,-0.12,1.46],"thirdMove":{"stardustToUnlock":75000,"candyToUnlock":75},"isTransferable":true,"isDeployable":true,"isTradable":true,"buddyGroupNumber":2}]