[{"pokemonId":"HERACROSS","modelScale":0.84,"type":"POKEMON_TYPE_BUG","type2":"POKEMON_TYPE_FIGHTING","camera":{"diskRadiusM":0.555,"cylinderRadiusM":1,"cylinderHeightM":1.6,"shoulderModeScale":0.5},"encounter":{"baseCaptureRate":0.3,"baseFleeRate":0.09,"collisionRadiusM":0.4,"collisionHeightM":1.2,"collisionHeadRadiusM":0.4,"movementType":"MOVEMENT_JUMP","movementTimerS":11,"jumpTimeS":1,"attackTimerS":20,"attackProbability":0.2,"dodgeProbability":0.15,"dodgeDurationS":1,"dodgeDistance":1,"cameraDistance":5.25,"minPokemonActionFrequencyS":0.2,"maxPokemonActionFrequencyS":1.6},"stats":{"baseStamina":190,"baseAttack":234,"baseDefense":179},"quickMoves":["COUNTER_FAST","STRUGGLE_BUG_FAST"],"cinematicMoves":["MEGAHORN","CLOSE_COMBAT","EARTHQUAKE","ROCK_BLAST"],"animationTime":[1.3333,0.6667,1.6667,2,0,2,3,3],"evolutionPips":1,"pokedexHeightM":1.5,"pokedexWeightKg":54,"heightStdDev":0.1875,"weightStdDev":6.75,"familyId":"FAMILY_HERACROSS","kmBuddyDistance":3,"buddySize":"BUDDY_BIG","modelHeight":1.5,"modelScaleV2":1,"buddyOffsetMale":[8.96,0,41.27],"buddyOffsetFemale":[8.96,0,41.27],"buddyScale":19,"thirdMove":{"stardustToUnlock":50000,"candyToUnlock":50},"isTransferable":true,"isDeployable":true,"isTradable":true,"buddyGroupNumber":3}]