[{"pokemonId":"KINGDRA","modelScale":0.78,"type":"POKEMON_TYPE_WATER","type2":"POKEMON_TYPE_DRAGON","camera":{"diskRadiusM":0.555,"cylinderRadiusM":0.85,"cylinderHeightM":2,"cylinderGroundM":0.64102566,"shoulderModeScale":0.5},"encounter":{"baseCaptureRate":0.1,"baseFleeRate":0.05,"collisionRadiusM":0.4,"collisionHeightM":0.3,"collisionHeadRadiusM":0.45,"movementType":"MOVEMENT_HOVERING","movementTimerS":11,"jumpTimeS":1,"attackTimerS":20,"bonusCandyCaptureReward":7,"bonusStardustCaptureReward":400,"attackProbability":0.1,"dodgeProbability":0.15,"dodgeDurationS":1,"dodgeDistance":1,"cameraDistance":4.875,"minPokemonActionFrequencyS":0.2,"maxPokemonActionFrequencyS":1.6,"bonusXlCandyCaptureReward":2,"shadowFormBaseCaptureRate":0.1,"shadowFormAttackProbability":0.7,"shadowFormDodgeProbability":0.2},"stats":{"baseStamina":181,"baseAttack":194,"baseDefense":194},"quickMoves":["WATERFALL_FAST","DRAGON_BREATH_FAST"],"cinematicMoves":["HYDRO_PUMP","BLIZZARD","OUTRAGE","OCTAZOOKA"],"animationTime":[1.3333,0.6667,1.6667,2,0,2,3,3],"evolutionPips":1,"pokedexHeightM":1.8,"pokedexWeightKg":152,"parentPokemonId":"SEADRA","heightStdDev":0.225,"weightStdDev":19,"familyId":"FAMILY_HORSEA","kmBuddyDistance":3,"buddySize":"BUDDY_BIG","modelHeight":1.8,"modelScaleV2":1,"buddyOffsetMale":[20,-33.6,41.58],"buddyOffsetFemale":[20,-33.6,41.58],"buddyScale":19,"thirdMove":{"stardustToUnlock":50000,"candyToUnlock":50},"isTransferable":true,"isDeployable":true,"isTradable":true,"shadow":{"purificationStardustNeeded":3000,"purificationCandyNeeded":3,"purifiedChargeMove":"RETURN","shadowChargeMove":"FRUSTRATION"},"buddyGroupNumber":3,"eliteQuickMove":["WATER_GUN_FAST"]},{"pokemonId":"KINGDRA","modelScale":0.78,"type":"POKEMON_TYPE_WATER","type2":"POKEMON_TYPE_DRAGON","camera":{"diskRadiusM":0.555,"cylinderRadiusM":0.85,"cylinderHeightM":2,"cylinderGroundM":0.64102566,"shoulderModeScale":0.5},"encounter":{"baseCaptureRate":0.1,"baseFleeRate":0.05,"collisionRadiusM":0.4,"collisionHeightM":0.3,"collisionHeadRadiusM":0.45,"movementType":"MOVEMENT_HOVERING","movementTimerS":11,"jumpTimeS":1,"attackTimerS":20,"bonusCandyCaptureReward":7,"bonusStardustCaptureReward":400,"attackProbability":0.1,"dodgeProbability":0.15,"dodgeDurationS":1,"dodgeDistance":1,"cameraDistance":4.875,"minPokemonActionFrequencyS":0.2,"maxPokemonActionFrequencyS":1.6,"bonusXlCandyCaptureReward":2,"shadowFormBaseCaptureRate":0.1,"shadowFormAttackProbability":0.7,"shadowFormDodgeProbability":0.2},"stats":{"baseStamina":181,"baseAttack":194,"baseDefense":194},"quickMoves":["WATERFALL_FAST","DRAGON_BREATH_FAST"],"cinematicMoves":["HYDRO_PUMP","BLIZZARD","OUTRAGE","OCTAZOOKA"],"animationTime":[1.3333,0.6667,1.6667,2,0,2,3,3],"evolutionPips":1,"pokedexHeightM":1.8,"pokedexWeightKg":152,"parentPokemonId":"SEADRA","heightStdDev":0.225,"weightStdDev":19,"familyId":"FAMILY_HORSEA","kmBuddyDistance":3,"buddySize":"BUDDY_BIG","modelHeight":1.8,"modelScaleV2":1,"form":"KINGDRA_NORMAL","buddyOffsetMale":[20,-33.6,41.58],"buddyOffsetFemale":[20,-33.6,41.58],"buddyScale":19,"thirdMove":{"stardustToUnlock":50000,"candyToUnlock":50},"isTransferable":true,"isDeployable":true,"isTradable":true,"shadow":{"purificationStardustNeeded":3000,"purificationCandyNeeded":3,"purifiedChargeMove":"RETURN","shadowChargeMove":"FRUSTRATION"},"buddyGroupNumber":3,"eliteQuickMove":["WATER_GUN_FAST"]}]