[{"pokemonId":"ROSERADE","modelScale":1.26,"type":"POKEMON_TYPE_GRASS","type2":"POKEMON_TYPE_POISON","camera":{"diskRadiusM":0.378,"cylinderRadiusM":0.18,"cylinderHeightM":0.9,"shoulderModeScale":0.5},"encounter":{"baseCaptureRate":0.15,"baseFleeRate":0.07,"collisionRadiusM":0.16,"collisionHeightM":0.252,"collisionHeadRadiusM":0.17,"movementType":"MOVEMENT_JUMP","movementTimerS":10,"jumpTimeS":0.9,"attackTimerS":29,"bonusCandyCaptureReward":2,"bonusStardustCaptureReward":200,"attackProbability":0.2,"dodgeProbability":0.3,"dodgeDurationS":1,"dodgeDistance":1,"cameraDistance":3,"minPokemonActionFrequencyS":0.2,"maxPokemonActionFrequencyS":1.6,"bonusXlCandyCaptureReward":1},"stats":{"baseStamina":155,"baseAttack":243,"baseDefense":185},"quickMoves":["POISON_JAB_FAST","RAZOR_LEAF_FAST"],"cinematicMoves":["SOLAR_BEAM","SLUDGE_BOMB","DAZZLING_GLEAM","GRASS_KNOT","LEAF_STORM"],"animationTime":[1.9,0.6667,1.8,1.7667,0,2.4,0.8667,0],"evolutionPips":1,"pokedexHeightM":0.9,"pokedexWeightKg":14.5,"parentPokemonId":"ROSELIA","heightStdDev":0.1125,"weightStdDev":1.8125,"familyId":"FAMILY_ROSELIA","candyToEvolve":25,"kmBuddyDistance":3,"modelHeight":0.9,"modelScaleV2":1,"buddyOffsetMale":[0,0,0],"buddyOffsetFemale":[0,0,0],"buddyScale":19,"buddyPortraitOffset":[0,-0.125,0.017],"thirdMove":{"stardustToUnlock":50000,"candyToUnlock":50},"isTransferable":true,"isDeployable":true,"isTradable":true,"buddyGroupNumber":2,"eliteQuickMove":["BULLET_SEED_FAST"],"eliteCinematicMove":["WEATHER_BALL_FIRE"]}]