[{"pokemonId":"SLOWKING","modelScale":0.74,"type":"POKEMON_TYPE_WATER","type2":"POKEMON_TYPE_PSYCHIC","camera":{"diskRadiusM":0.555,"cylinderRadiusM":0.75,"cylinderHeightM":2,"shoulderModeScale":0.5},"encounter":{"baseCaptureRate":0.1,"baseFleeRate":0.05,"collisionRadiusM":0.6,"collisionHeightM":0.91,"collisionHeadRadiusM":0.4,"movementTimerS":11,"jumpTimeS":2,"attackTimerS":20,"bonusCandyCaptureReward":2,"bonusStardustCaptureReward":200,"attackProbability":0.05,"dodgeProbability":0.05,"dodgeDurationS":1,"dodgeDistance":1,"cameraDistance":4.2,"minPokemonActionFrequencyS":0.2,"maxPokemonActionFrequencyS":1.6,"bonusXlCandyCaptureReward":1,"shadowFormBaseCaptureRate":0.1,"shadowFormAttackProbability":0.7,"shadowFormDodgeProbability":0.2},"stats":{"baseStamina":216,"baseAttack":177,"baseDefense":180},"quickMoves":["WATER_GUN_FAST","CONFUSION_FAST"],"cinematicMoves":["BLIZZARD","PSYCHIC","FIRE_BLAST"],"animationTime":[1.3333,0.6667,1.6667,2,0,2,3,3],"evolutionPips":1,"pokedexHeightM":2.01,"pokedexWeightKg":79.5,"parentPokemonId":"SLOWPOKE","heightStdDev":0.25125,"weightStdDev":9.9375,"familyId":"FAMILY_SLOWPOKE","kmBuddyDistance":3,"buddySize":"BUDDY_BIG","modelHeight":2,"modelScaleV2":1,"buddyOffsetMale":[25,0,32.61],"buddyOffsetFemale":[25,0,32.61],"buddyScale":19,"buddyPortraitOffset":[-0.05,-0.3,-0.32],"thirdMove":{"stardustToUnlock":50000,"candyToUnlock":50},"isTransferable":true,"isDeployable":true,"isTradable":true,"shadow":{"purificationStardustNeeded":3000,"purificationCandyNeeded":3,"purifiedChargeMove":"RETURN","shadowChargeMove":"FRUSTRATION"},"buddyGroupNumber":3,"buddyWalkedMegaEnergyAward":15},{"pokemonId":"SLOWKING","type":"POKEMON_TYPE_POISON","type2":"POKEMON_TYPE_PSYCHIC","camera":{"cylinderRadiusM":0.75,"cylinderHeightM":2},"encounter":{"baseCaptureRate":0.1,"baseFleeRate":0.05,"collisionRadiusM":0.6,"collisionHeightM":0.91,"collisionHeadRadiusM":0.4,"jumpTimeS":2,"bonusCandyCaptureReward":2,"bonusStardustCaptureReward":200,"attackProbability":0.05,"dodgeProbability":0.05,"dodgeDurationS":1,"dodgeDistance":1,"cameraDistance":4.2,"minPokemonActionFrequencyS":0.2,"maxPokemonActionFrequencyS":1.6,"bonusXlCandyCaptureReward":1,"shadowFormBaseCaptureRate":0.1,"shadowFormAttackProbability":0.7,"shadowFormDodgeProbability":0.2},"stats":{"baseStamina":216,"baseAttack":190,"baseDefense":180},"quickMoves":["HEX_FAST","CONFUSION_FAST","ACID_FAST"],"cinematicMoves":["FUTURESIGHT","SHADOW_BALL","SLUDGE_WAVE"],"pokedexHeightM":1.8,"pokedexWeightKg":79.5,"parentPokemonId":"SLOWPOKE","heightStdDev":0.225,"weightStdDev":9.9375,"familyId":"FAMILY_SLOWPOKE","kmBuddyDistance":3,"buddySize":"BUDDY_BIG","modelHeight":2,"modelScaleV2":1,"form":"SLOWKING_GALARIAN","buddyOffsetMale":[25,0,32.61],"buddyOffsetFemale":[25,0,32.61],"buddyScale":19,"buddyPortraitOffset":[-0.05,-0.3,-0.32],"thirdMove":{"stardustToUnlock":50000,"candyToUnlock":50},"isTransferable":true,"isDeployable":true,"isTradable":true,"shadow":{"purificationStardustNeeded":3000,"purificationCandyNeeded":3,"purifiedChargeMove":"RETURN","shadowChargeMove":"FRUSTRATION"},"buddyGroupNumber":3,"buddyWalkedMegaEnergyAward":15},{"pokemonId":"SLOWKING","modelScale":0.74,"type":"POKEMON_TYPE_WATER","type2":"POKEMON_TYPE_PSYCHIC","camera":{"diskRadiusM":0.555,"cylinderRadiusM":0.75,"cylinderHeightM":2,"shoulderModeScale":0.5},"encounter":{"baseCaptureRate":0.1,"baseFleeRate":0.05,"collisionRadiusM":0.6,"collisionHeightM":0.91,"collisionHeadRadiusM":0.4,"movementTimerS":11,"jumpTimeS":2,"attackTimerS":20,"bonusCandyCaptureReward":2,"bonusStardustCaptureReward":200,"attackProbability":0.05,"dodgeProbability":0.05,"dodgeDurationS":1,"dodgeDistance":1,"cameraDistance":4.2,"minPokemonActionFrequencyS":0.2,"maxPokemonActionFrequencyS":1.6,"bonusXlCandyCaptureReward":1,"shadowFormBaseCaptureRate":0.1,"shadowFormAttackProbability":0.7,"shadowFormDodgeProbability":0.2},"stats":{"baseStamina":216,"baseAttack":177,"baseDefense":180},"quickMoves":["WATER_GUN_FAST","CONFUSION_FAST"],"cinematicMoves":["BLIZZARD","PSYCHIC","FIRE_BLAST"],"animationTime":[1.3333,0.6667,1.6667,2,0,2,3,3],"evolutionPips":1,"pokedexHeightM":2.01,"pokedexWeightKg":79.5,"parentPokemonId":"SLOWPOKE","heightStdDev":0.25125,"weightStdDev":9.9375,"familyId":"FAMILY_SLOWPOKE","kmBuddyDistance":3,"buddySize":"BUDDY_BIG","modelHeight":2,"modelScaleV2":1,"form":"SLOWKING_NORMAL","buddyOffsetMale":[25,0,32.61],"buddyOffsetFemale":[25,0,32.61],"buddyScale":19,"buddyPortraitOffset":[-0.05,-0.3,-0.32],"thirdMove":{"stardustToUnlock":50000,"candyToUnlock":50},"isTransferable":true,"isDeployable":true,"isTradable":true,"shadow":{"purificationStardustNeeded":3000,"purificationCandyNeeded":3,"purifiedChargeMove":"RETURN","shadowChargeMove":"FRUSTRATION"},"buddyGroupNumber":3,"buddyWalkedMegaEnergyAward":15}]