[{"pokemonId":"SNORLAX","modelScale":0.74,"type":"POKEMON_TYPE_NORMAL","camera":{"diskRadiusM":1.11,"cylinderRadiusM":1.15,"cylinderHeightM":2,"shoulderModeScale":0.5},"encounter":{"baseCaptureRate":0.05,"baseFleeRate":0.09,"collisionRadiusM":0.74,"collisionHeightM":1.11,"collisionHeadRadiusM":0.481,"movementType":"MOVEMENT_JUMP","movementTimerS":3,"jumpTimeS":1,"attackTimerS":8,"attackProbability":0.1,"dodgeProbability":0.05,"dodgeDurationS":1,"dodgeDistance":1,"cameraDistance":5.55,"minPokemonActionFrequencyS":0.2,"maxPokemonActionFrequencyS":1.6,"shadowFormBaseCaptureRate":0.05,"shadowFormAttackProbability":0.7,"shadowFormDodgeProbability":0.2},"stats":{"baseStamina":330,"baseAttack":190,"baseDefense":169},"quickMoves":["ZEN_HEADBUTT_FAST","LICK_FAST"],"cinematicMoves":["HEAVY_SLAM","HYPER_BEAM","EARTHQUAKE","OUTRAGE","SKULL_BASH","BODY_SLAM","SUPER_POWER"],"animationTime":[2.4,0.6667,1.8333,1.6667,0,2.5,2.5,2.333333],"evolutionPips":1,"pokedexHeightM":2.1,"pokedexWeightKg":460,"parentPokemonId":"MUNCHLAX","heightStdDev":0.2625,"weightStdDev":57.5,"familyId":"FAMILY_SNORLAX","kmBuddyDistance":5,"buddySize":"BUDDY_BIG","modelHeight":2,"modelScaleV2":1,"buddyOffsetMale":[10,0,28.01],"buddyOffsetFemale":[10,0,28.01],"buddyScale":19,"buddyPortraitOffset":[0,-0.18,0],"thirdMove":{"stardustToUnlock":75000,"candyToUnlock":75},"isTransferable":true,"isDeployable":true,"combatShoulderCameraAngle":[2.5,1,1.5],"isTradable":true,"combatDefaultCameraAngle":[2.7,2,2],"shadow":{"purificationStardustNeeded":5000,"purificationCandyNeeded":5,"purifiedChargeMove":"RETURN","shadowChargeMove":"FRUSTRATION"},"buddyGroupNumber":3,"eliteQuickMove":["YAWN_FAST"]},{"pokemonId":"SNORLAX","modelScale":0.74,"type":"POKEMON_TYPE_NORMAL","camera":{"diskRadiusM":1.11,"cylinderRadiusM":1.15,"cylinderHeightM":2,"shoulderModeScale":0.5},"encounter":{"baseCaptureRate":0.05,"baseFleeRate":0.09,"collisionRadiusM":0.74,"collisionHeightM":1.11,"collisionHeadRadiusM":0.481,"movementType":"MOVEMENT_JUMP","movementTimerS":3,"jumpTimeS":1,"attackTimerS":8,"attackProbability":0.1,"dodgeProbability":0.05,"dodgeDurationS":1,"dodgeDistance":1,"cameraDistance":5.55,"minPokemonActionFrequencyS":0.2,"maxPokemonActionFrequencyS":1.6,"shadowFormBaseCaptureRate":0.05,"shadowFormAttackProbability":0.7,"shadowFormDodgeProbability":0.2},"stats":{"baseStamina":330,"baseAttack":190,"baseDefense":169},"quickMoves":["ZEN_HEADBUTT_FAST","LICK_FAST"],"cinematicMoves":["HEAVY_SLAM","HYPER_BEAM","EARTHQUAKE","OUTRAGE","SKULL_BASH","BODY_SLAM","SUPER_POWER"],"animationTime":[2.4,0.6667,1.8333,1.6667,0,2.5,2.5,2.333333],"evolutionPips":1,"pokedexHeightM":2.1,"pokedexWeightKg":460,"parentPokemonId":"MUNCHLAX","heightStdDev":0.2625,"weightStdDev":57.5,"familyId":"FAMILY_SNORLAX","kmBuddyDistance":5,"buddySize":"BUDDY_BIG","modelHeight":2,"modelScaleV2":1,"form":"SNORLAX_NORMAL","buddyOffsetMale":[10,0,28.01],"buddyOffsetFemale":[10,0,28.01],"buddyScale":19,"buddyPortraitOffset":[0,-0.18,0],"thirdMove":{"stardustToUnlock":75000,"candyToUnlock":75},"isTransferable":true,"isDeployable":true,"combatShoulderCameraAngle":[2.5,1,1.5],"isTradable":true,"combatDefaultCameraAngle":[2.7,2,2],"shadow":{"purificationStardustNeeded":5000,"purificationCandyNeeded":5,"purifiedChargeMove":"RETURN","shadowChargeMove":"FRUSTRATION"},"buddyGroupNumber":3,"eliteQuickMove":["YAWN_FAST"]}]