{"title":"2018-05-31","virtualPath":"/Diary/","html":"昨夕は七尾方面へ。<br />\n七尾あたりのトレーナはばっちり LINE で繋がってるらしく、仕事が終わった後はかなりの確度で人が集まるらしい。<br />\nしかし、そういう状況だとみんなのポケマップみたいなのに登録する意味がないので、誰も登録しないとのこと。なるほどー。<br />\n個人的にはそれでもマップに登録してあると旅人、出張人がふらりと散歩がてらに混じれるので登録するかな。<br />\n<br />\n昨日は第一陣で 20 名越えてるところもあり。とはいえ複垢多数だけども。二台持ちは 5,6 人、というところか。<br />\n<br />\n七尾市内滞在二時間ほどで、金沢にいるときよりもはるかに多い、4 回レイド成立。運もよかったのかな。<br />\n田舎だけに車が停めやすい、というポイントもあるか。<br />\n<br />\n星5 * 3, バンギ * 1<br />\n","styles":["/css/github-markdown.css","/css/markdown-include.css"],"description":"日記","updated":"2020-07-12T03:29:49","published":"2020-07-12T03:29:49"}