{"title":"2025-04-05","virtualPath":"/Diary/","anchorId":"Nzj8Nw_4_l","anchorLink":"/Gitwee/timeline/2025/04/05","description":"\u65e5\u8a18,\u3064\u3076\u3084\u304d,\u96d1\u8a18\u5e33,\u30e2\u30f3\u30cf\u30f3Now","tags":[{"title":"\u30e2\u30f3\u30cf\u30f3Now","tagkey":"Ga9v46pU3Ch7xz2sKLEMdA","link":"/Gitwee/tag/Ga9v46pU3Ch7xz2sKLEMdA"}],"html":"<div class=\"markdown-body\"><p>HR300 \u5230\u9054</p>\n\n<p><a target=\"_blank\" rel=\"noopener noreferrer\" href=\"/MyContents2025/2025-04-05/Nzj8Nw_4_ly6aDsR/dffa3358b3bc331d97536d676756835f.jpg\"><img src=\"/MyContents2025/2025-04-05/Nzj8Nw_4_ly6aDsR/dffa3358b3bc331d97536d676756835f.jpg\" alt=\"\" style=\"max-width: 100%;\"></a></p>\n</div>","styles":["/css/github-markdown.css","/css/markdown-include.css"],"updated":"2025-04-05T22:14:43","published":"2025-04-05T22:14:43","updatedAt":"2025-04-05T13:14:43.00Z","publishedAt":"2025-04-05T13:14:43.00Z"}