{"title":"2021-09-29","virtualPath":"/Diary/","anchorId":"XotIYEFtD8","anchorLink":"/Gitwee/timeline/2021/09/29","description":"\u65e5\u8a18,\u3064\u3076\u3084\u304d,\u96d1\u8a18\u5e33","tags":[{"title":"\u30dd\u30b1\u30e2\u30f3go","tagkey":"lxfDm7aaLlErPTsvONpziw","link":"/Gitwee/tag/lxfDm7aaLlErPTsvONpziw"}],"html":"<div class=\"markdown-body\">\n<p><a href=\"/MyContents2021/2021-09-29/XotIYEFtD8OdNpsH/20210929-220454-Screenshot_20210929-220454352.jpg\" target=\"_blank\" rel=\"noopener noreferrer\"><img src=\"/MyContents2021/2021-09-29/XotIYEFtD8OdNpsH/20210929-220454-Screenshot_20210929-220454352.jpg\" alt=\"\" style=\"max-width:100%;\"></a></p>\n<p>\u30b6\u30b7\u30a2\u30f3\u306e\u6280\u69cb\u6210\u3092\u898b\u76f4\u3057\u3066\u3088\u3046\u3084\u304f\u8abf\u5b50\u304c\u4e0a\u304c\u3063\u3066\u304d\u305f\u300212 \u9023\u52dd\u3002</p>\n<p>\u4eca\u65e5\u306e\u30ec\u30a4\u30c9\u30a2\u30ef\u30fc\u306f\u62db\u5f85\u306f\u304d\u3066\u305f\u307f\u305f\u3044\u3060\u3051\u3069\u3001\u901a\u77e5\u304c\u3053\u306a\u304f\u3066\u5168\u90e8\u53d6\u308a\u3053\u307c\u3057\u305f\u3002\u4eca\u30b7\u30ea\u30fc\u30ba\u306e\u8272\u9055\u3044\u306f\u306a\u3057\u3060\u306a\u3002 <g-emoji class=\"g-emoji\" alias=\"disappointed\" fallback-src=\"https://github.githubassets.com/images/icons/emoji/unicode/1f61e.png\">\ud83d\ude1e</g-emoji></p>\n<p>\u62db\u5f85\u306e\u5c65\u6b74\u3067\u3082\u307f\u308c\u306a\u3044\u304b\u306a\u3002\u8ab0\u304c\u62db\u5f85\u3057\u3066\u304f\u308c\u305f\u304b\u3082\u5206\u304b\u3089\u3093\u3002</p>\n</div>","styles":["/css/github-markdown.css","/css/markdown-include.css"],"updated":"2021-09-30T12:01:16","published":"2021-09-30T12:01:16"}