{"title":"2023-03-09","virtualPath":"/Diary/","anchorId":"_4UOCxbNg0","anchorLink":"/Gitwee/timeline/2023/03/09","description":"\u65e5\u8a18,\u3064\u3076\u3084\u304d,\u96d1\u8a18\u5e33,\u30b9\u30dd\u30fc\u30c4,\u91ce\u7403","tags":[{"title":"\u30b9\u30dd\u30fc\u30c4","tagkey":"CqCq2ZcXnUxsvdDkN9pGxQ","link":"/Gitwee/tag/CqCq2ZcXnUxsvdDkN9pGxQ"},{"title":"\u91ce\u7403","tagkey":"njECRi6rlhs27w1kqVToPA","link":"/Gitwee/tag/njECRi6rlhs27w1kqVToPA"}],"html":"<div class=\"markdown-body\"><p>\u30cc\u30fc\u30c8\u30d0\u30fc\u3063\u3066\u3068\u304d\u3069\u304d\u9a12\u3044\u3067\u308b\u306a\u3063\u3066\u601d\u3063\u305f\u3089\u3001\u91ce\u7403\u306e\u5e30\u5316\u9078\u624b\u306a\u306e\u304b\u306a\u3002</p>\n<p><a href=\"https://ja.wikipedia.org/wiki/%E3%83%A9%E3%83%BC%E3%82%BA%E3%83%BB%E3%83%8C%E3%83%BC%E3%83%88%E3%83%90%E3%83%BC\" rel=\"nofollow\">\u30e9\u30fc\u30ba\u30fb\u30cc\u30fc\u30c8\u30d0\u30fc - Wikipedia</a></p>\n<p>\u3093\u30fc\uff1f\u306a\u3093\u3060\u308d\u3002\u56fd\u7c4d\u306f\u30a2\u30e1\u30ea\u30ab\u306b\u306a\u3063\u3066\u308b\u306d\u3002\u5404\u56fd\u306e\u30c1\u30fc\u30e0\u306b\u5165\u308b\u305f\u3081\u306e\u898f\u5247\u304c\u56fd\u7c4d\u4ee5\u5916\u306b\u4f55\u304b\u3042\u308b\u306e\u304b\u3002</p>\n</div>","styles":["/css/github-markdown.css","/css/markdown-include.css"],"updated":"2023-03-09T10:59:41","published":"2023-03-09T10:59:41","updatedAt":"2023-03-09T01:59:41.00Z","publishedAt":"2023-03-09T01:59:41.00Z"}