{"title":"内灘のアレ","virtualPath":null,"html":"<a href=\"../\">戻る</a><div><img class=\"author-photo\" src=\"https://lh3.googleusercontent.com/a/default-user=s64-c\" alt=\"神楽\" /><a href=\"https://plus.google.com/106507564317880442914\" target=\"_blank\" class=\"author\">神楽</a> - <a target=\"_blank\" href=\"https://plus.google.com/106507564317880442914/posts/6vC1AEzLZdn\">2017-05-20 19:06:50+0900</a><span>- Updated: 2017-05-20 19:06:50+0900</span></div><div class=\"main-content\">P8 Lawson だ、と思って駐車場みたら何度も見た車があった。今の Lawson は Agent ほいほい。<br /><br />みなまで言いませんが、あのナイスミドル風なおじさまが暗い車内に一人でスマホ二台持ちして交互にバースターぶっぱなしてたのか。スキャナ + comm + G+ 上の人物像と一致しなさすぎてかなり動揺したわw 面白いもんだねぇ。<br /><br />顔も見ることできたし、今度こそもうどうでもいいやw<br /><br />でも、できればアカウント名は変えてくれませんかね、100 円やるから…<br /></div>","styles":["/css/googleplus.css"],"description":"Google+,随筆","updated":"2019-12-10T20:14:40","published":"2019-02-12T03:08:49"}