{"title":"2019-09-15","virtualPath":"/Diary/","html":"<div class=\"markdown-body\"><p>かほく市に点在する○○五福館って名称はどこから来てるんだろ。ただの集会所みたいなんだけど？</p>\n<hr>\n<p><a href=\"https://twitter.com/kanata_fgo6/status/1172095585815449600/photo/1\" rel=\"nofollow\">https://twitter.com/kanata_fgo6/status/1172095585815449600/photo/1</a></p>\n<p>剱岳で twitter 検索したら槍の穂先とかをスーツで縦走したとかいう意味不明なのが目に入ってきた。それだけなら勝手にすればなんだけど、その後の受け答えが、さすがになんとも名状し難い。いや、いくらなんでもアホすぎて笑ってるww</p>\n<p>ネット界隈ってこのレベルのアホがときどき発掘されて、やはり面白い。表現規制はするべきではないよね。</p>\n<p>もちろん、こんなところでスーツなんて買うわけがない。ネタ元は暇なときにでも探してみるわw</p>\n<hr>\n<p>数日ニュースに触れてなかったので今気付いて剱岳の滑落事故を読んだ。メディア媒体での扱いよりも twitter で拡散するの、亡くなった人の属性に起因するものだよなぁ。コメント投げてる人、場合によってはご遺族の心を抉るものになると思うが、理解しているや否や。例の匿名掲示板っぽいまとめのタイトルなんて目にするだけで胸糞だぜ？</p>\n<p>twitter に投下したら、コメント投げてる人と一緒になる気がした。ここに吐き出しとこう。</p>\n<hr>\n<p>黒部五郎岳小舎で理屈っぽいおじさんにあれこれと聞かれたんだけど、ときどき「暗くなっても下山しない」とかで騒ぎになってるのってああいう人が起こしてる仮想騒ぎなのでは。こちらは暗い時間に登山開始してるんだよね。泰山鳴動して鼠一匹。</p>\n<p>下山中にじいちゃんを追い越したんだけど、何も聞こえてこないし、たぶん大丈夫だったのだろう。</p>\n<hr>\n<p>いつの間にか金ずりが 200 越えてた。脱出率の低いデオキシス出てるからかな。</p>\n<hr>\n<p>コミュニティデイは不参加。いくつか手持ちを進化させただけ。</p>\n</div>","styles":["/css/github-markdown.css","/css/markdown-include.css"],"description":"日記,つぶやき,雑記帳","updated":"2019-09-28T03:41:29","published":"2019-09-28T03:41:29"}