{"title":"2022-07-06","virtualPath":"/Diary/","anchorId":"bnJfby6wh_","anchorLink":"/Gitwee/timeline/2022/07/06","description":"\u65e5\u8a18,\u3064\u3076\u3084\u304d,\u96d1\u8a18\u5e33,\u30dd\u30b1\u30e2\u30f3go","tags":[{"title":"\u30dd\u30b1\u30e2\u30f3go","tagkey":"lxfDm7aaLlErPTsvONpziw","link":"/Gitwee/tag/lxfDm7aaLlErPTsvONpziw"}],"html":"<div class=\"markdown-body\"><p>\u4eca\u65e5\u306e\u30d5\u30ea\u30fc\u30b6\u30fc\u306f\u4e00\u4ef6\u3082\u30ea\u30e2\u30fc\u30c8\u62db\u5f85\u304c\u3053\u306a\u304b\u3063\u305f\u3002\u9759\u304b\u306a\u3082\u3093\u3060\u3002</p>\n</div>","styles":["/css/github-markdown.css","/css/markdown-include.css"],"updated":"2022-07-06T04:50:42","published":"2022-07-06T04:50:42","updatedAt":"2022-07-05T19:50:42.00Z","publishedAt":"2022-07-05T19:50:42.00Z"}