{"title":"2022-09-06","virtualPath":"/Diary/","anchorId":"eCMwgXmi1E","anchorLink":"/Gitwee/timeline/2022/09/06","description":"\u65e5\u8a18,\u3064\u3076\u3084\u304d,\u96d1\u8a18\u5e33,\u30dd\u30b1\u30e2\u30f3go","tags":[{"title":"\u30dd\u30b1\u30e2\u30f3go","tagkey":"lxfDm7aaLlErPTsvONpziw","link":"/Gitwee/tag/lxfDm7aaLlErPTsvONpziw"}],"html":"<div class=\"markdown-body\"><p><a href=\"https://9db.jp/pokemongo/data/2734?lv=4&amp;id=9672&amp;o=1&amp;pl=40.5\" rel=\"nofollow\">\u3010\u30dd\u30b1\u30e2\u30f3GO\u3011\u30ab\u30a6\u30f3\u30bf\u30fc\u30ea\u30b9\u30c8 / \u5bfe\u7b56\u30dd\u30b1\u30e2\u30f3</a></p>\n<p>\u30e1\u30ac\u30d5\u30fc\u30c7\u30a3\u30f3\u306e\u30bd\u30ed\u306f\u2026 \u7121\u7406\u304b\u3002</p>\n<p>\u30c7\u30aa\u30ad\u30b7\u30b9\u306e\u30a2\u30bf\u30c3\u30af\u306f\u3001\u99d2\u304c\u63c3\u3063\u3066\u304d\u305f\u304b\u3089 80 \u79d2\u3050\u3089\u3044\u6b8b\u3057\u3066\u697d\u52dd\u306b\u306a\u3063\u3066\u3044\u305f\u3002</p>\n</div>","styles":["/css/github-markdown.css","/css/markdown-include.css"],"updated":"2022-09-06T12:40:17","published":"2022-09-06T12:40:17","updatedAt":"2022-09-06T03:40:17.00Z","publishedAt":"2022-09-06T03:40:17.00Z"}