{"title":"2021-09-13","virtualPath":"/Diary/","anchorId":"IvlaYyn67y","anchorLink":"/Gitwee/timeline/2021/09/13","description":"\u65e5\u8a18,\u3064\u3076\u3084\u304d,\u96d1\u8a18\u5e33","tags":[{"title":"Ingress","tagkey":"fQXHCLkrSAm_6b9m7fj3ZQ","link":"/Gitwee/tag/fQXHCLkrSAm_6b9m7fj3ZQ"},{"title":"\u4f4d\u7f6e\u507d\u88c5","tagkey":"hZknHLYAiAaZtY6eS_3nmA","link":"/Gitwee/tag/hZknHLYAiAaZtY6eS_3nmA"},{"title":"\u5317\u9678","tagkey":"4X6wZQYq4Z45gOkjq2R9rg","link":"/Gitwee/tag/4X6wZQYq4Z45gOkjq2R9rg"}],"html":"<div class=\"markdown-body\"><p>\u307e\u305f\u5225\u5c71\u304c\u767d\u304f\u306a\u3063\u3066\u305f\u3002</p>\n\n<p><a href=\"/MyContents2021/2021-09-13/IvlaYyn67yL5QwQZ/20210912-121506-Screenshot_20210912-121506405.jpg\" target=\"_blank\" rel=\"noopener noreferrer\"><img src=\"/MyContents2021/2021-09-13/IvlaYyn67yL5QwQZ/20210912-121506-Screenshot_20210912-121506405.jpg\" alt=\"\" style=\"max-width:100%;\"></a></p>\n<pre><code>2021-09-12 10:35:58\t&lt;Samurayiuy&gt;\tlinked \u5fb3\u53b3\u5bfa to \u5fdc\u884c\u5bfa\n2021-09-12 11:27:07\t&lt;Samurayiuy&gt;\tdestroyed a Resonator on \u5225\u5c71\u3000\u5c71\u9802\n</code></pre>\n<p>\u4e0b\u754c(\u8d8a\u524d\u5927\u91ce)\u3067\u30ec\u30d9\u30eb\u4e0a\u3052\u3066\u304b\u3089\u767d\u5c71\u5225\u5c71\u3078 1 \u6642\u9593\u3067\u3073\u3085\u30fc\u3093\u3002</p>\n<pre><code>2021-09-12 10:17:57\t&lt;Samurayiuy&gt;\t[faction] concluiu seu Treinamento de Agente\n2021-09-12 10:35:58\t&lt;Samurayiuy&gt;\tlinked \u5fb3\u53b3\u5bfa to \u5fdc\u884c\u5bfa\n</code></pre>\n<p>\u4eca\u5ea6\u306f\u30dd\u30eb\u30c8\u30ac\u30eb\u8a9e\u3002\u30ec\u30d9\u30eb\u3092\u5145\u5206\u307e\u3067\u4e0a\u3052\u304d\u308b\u306e\u306b 20 \u5206\u307b\u3069\u304b\u3002</p>\n</div>","styles":["/css/github-markdown.css","/css/markdown-include.css"],"updated":"2021-09-13T11:30:45","published":"2021-09-13T09:44:55"}