{"title":"2023-04-11","virtualPath":"/Diary/","anchorId":"YjJ9u7nz8o","anchorLink":"/Gitwee/timeline/2023/04/11","description":"\u65e5\u8a18,\u3064\u3076\u3084\u304d,\u96d1\u8a18\u5e33,Web,\u708e\u4e0a","tags":[{"title":"Web","tagkey":"xuGQsoRjPEjjnlUEnaPM6A","link":"/Gitwee/tag/xuGQsoRjPEjjnlUEnaPM6A"},{"title":"\u708e\u4e0a","tagkey":"YU0HrJ8q2ofz4H71bcfQHw","link":"/Gitwee/tag/YU0HrJ8q2ofz4H71bcfQHw"}],"html":"<div class=\"markdown-body\"><p>\u6687\u3042\u306e\u3093\u306e\u4eba\u9054\u3092\u4f55\u4eba\u304b\u30b9\u30c8\u30c3\u30af\u3057\u3066\u86f8\u58fa\u306e\u86f8\u3067\u3082\u773a\u3081\u308b\u3088\u3046\u306b\u89b3\u5bdf\u3057\u3066\u308b\u3093\u3060\u304c\u3001\u306a\u304b\u306a\u304b\u4e0d\u6c17\u5473\u3060\u306a\u3002\u3042\u308c\u306f\u304d\u3063\u3068\u982d\u304c\u5f31\u3044\u306e\u3060\u308d\u3046\u3002</p>\n<p>\u304b\u308f\u3044\u305d\u3046\u306b\u2026</p>\n</div>","styles":["/css/github-markdown.css","/css/markdown-include.css"],"updated":"2023-04-11T09:10:04","published":"2023-04-11T09:10:04","updatedAt":"2023-04-11T00:10:04.00Z","publishedAt":"2023-04-11T00:10:04.00Z"}