{"title":"2024-09-07","virtualPath":"/Diary/","anchorId":"QfxPBJ7PkW","anchorLink":"/Gitwee/timeline/2024/09/07","description":"\u65e5\u8a18,\u3064\u3076\u3084\u304d,\u96d1\u8a18\u5e33,\u30e2\u30f3\u30cf\u30f3Now","tags":[{"title":"\u30e2\u30f3\u30cf\u30f3Now","tagkey":"Ga9v46pU3Ch7xz2sKLEMdA","link":"/Gitwee/tag/Ga9v46pU3Ch7xz2sKLEMdA"}],"html":"<div class=\"markdown-body\"><p>\u6b66\u5668\u5f37\u5316\u306e\u5100 \u30bf\u30de\u30df\u30c4\u30cd\u592a\u5200 \u305f\u307e\u306e\u3092 G8-4, G8-5, G9-1</p>\n\n\n\n\n<p><a target=\"_blank\" rel=\"noopener noreferrer\" href=\"/MyContents2024/2024-09-07/QfxPBJ7PkW3rvAlk/67cc31525518e5819277d8b1f4f09f5a.jpg\"><img src=\"/MyContents2024/2024-09-07/QfxPBJ7PkW3rvAlk/67cc31525518e5819277d8b1f4f09f5a.jpg\" alt=\"\" style=\"max-width: 100%;\"></a>\n<a target=\"_blank\" rel=\"noopener noreferrer\" href=\"/MyContents2024/2024-09-07/QfxPBJ7PkW3rvAlk/a72f40265b086114e2b914e322ed5a35.jpg\"><img src=\"/MyContents2024/2024-09-07/QfxPBJ7PkW3rvAlk/a72f40265b086114e2b914e322ed5a35.jpg\" alt=\"\" title=\"G8-4\" style=\"max-width: 100%;\"></a>\n<a target=\"_blank\" rel=\"noopener noreferrer\" href=\"/MyContents2024/2024-09-07/QfxPBJ7PkW3rvAlk/6f4122a8197a06f3555cd3c7dc91c841.jpg\"><img src=\"/MyContents2024/2024-09-07/QfxPBJ7PkW3rvAlk/6f4122a8197a06f3555cd3c7dc91c841.jpg\" alt=\"\" title=\"G8-5\" style=\"max-width: 100%;\"></a>\n<a target=\"_blank\" rel=\"noopener noreferrer\" href=\"/MyContents2024/2024-09-07/QfxPBJ7PkW3rvAlk/cb55b3343b24c043830e42a9bafb6a24.jpg\"><img src=\"/MyContents2024/2024-09-07/QfxPBJ7PkW3rvAlk/cb55b3343b24c043830e42a9bafb6a24.jpg\" alt=\"\" title=\"G9-1\" style=\"max-width: 100%;\"></a></p>\n<p>\u96d1\u9b5a\u304b\u3089\u3068\u308c\u308b\u3068\u304c\u3063\u305f\u722a\u2026 \u4eca\u306e friend task \u306e\u9032\u307f\u65b9\u304b\u3089\u5bdf\u3059\u308b\u3068\u3001\u30ac\u30c1\u306e\u4eba\u9054\u3001\u96d1\u9b5a\u72e9\u308a\u3082\u76f8\u5f53\u306a\u91cf\u3053\u306a\u3057\u3066\u308b\u3002\u3068\u3066\u3082\u6575\u308f\u3093\u3002</p>\n</div>","styles":["/css/github-markdown.css","/css/markdown-include.css"],"updated":"2024-09-06T21:25:17","published":"2024-09-06T21:25:17","updatedAt":"2024-09-06T12:25:17.00Z","publishedAt":"2024-09-06T12:25:17.00Z"}