{"title":"2020-03-20","virtualPath":"/Diary/","anchorId":"krxcWoGSb_","anchorLink":"/Gitwee/timeline/2020/03/20","description":"\u65e5\u8a18,\u3064\u3076\u3084\u304d,\u96d1\u8a18\u5e33","tags":[{"title":"\u30dd\u30b1\u30e2\u30f3go","tagkey":"lxfDm7aaLlErPTsvONpziw","link":"/Gitwee/tag/lxfDm7aaLlErPTsvONpziw"}],"html":"<div class=\"markdown-body\"><p>\u4e95\u4e0a\u306e\u8358\u3082\u30ec\u30a4\u30c9\u505c\u3081\u3089\u308c\u305f\u307f\u305f\u3044\u3002\u3042\u305d\u3053\u306f\u6614\u304b\u3089 Ingress Agent \u306e\u4e00\u90e8\u3082\u3072\u3069\u304b\u3063\u305f\u304b\u3089\u306d\u3047\u3002</p>\n</div>","styles":["/css/github-markdown.css","/css/markdown-include.css"],"updated":"2020-11-26T18:25:17","published":"2020-11-26T18:25:17"}