{"title":"2021-07-16","virtualPath":"/Diary/","anchorId":"CCZiMHprRY","anchorLink":"/Gitwee/timeline/2021/07/16","description":"\u65e5\u8a18,\u3064\u3076\u3084\u304d,\u96d1\u8a18\u5e33","tags":[{"title":"Web","tagkey":"xuGQsoRjPEjjnlUEnaPM6A","link":"/Gitwee/tag/xuGQsoRjPEjjnlUEnaPM6A"},{"title":"\u6642\u4e8b","tagkey":"inkM5pkcdzCmwgjjDE5G-A","link":"/Gitwee/tag/inkM5pkcdzCmwgjjDE5G-A"}],"html":"<div class=\"markdown-body\"><p><a href=\"https://diamond.jp/articles/-/276916\" rel=\"nofollow\">\u4f0a\u85e4\u8a69\u7e54\u3055\u3093\u306e\u30cd\u30c3\u30c8\u8ab9\u8b17\u4e2d\u50b7\u8a34\u8a1f\u3067\u8003\u3048\u308b\u3001\u300c\u78ba\u4fe1\u72af\u300d\u3068\u306e\u7d42\u308f\u308a\u306a\u304d\u95d8\u3044 | News&amp;amp;Analysis | \u30c0\u30a4\u30e4\u30e2\u30f3\u30c9\u30fb\u30aa\u30f3\u30e9\u30a4\u30f3</a></p>\n<p>\u30ea\u30f3\u30af\u3057\u306a\u3044\u3051\u3069\u67d0 twitter \u30a2\u30ab\u30a6\u30f3\u30c8\u306f\u7fa4\u3089\u304c\u3063\u3066\u308b\u96c6\u56e3\u3082\u8ad6\u8abf\u3082\u76f8\u5909\u308f\u3089\u305a\u3060\u306a\u3002<g-emoji class=\"g-emoji\" alias=\"sweat_smile\" fallback-src=\"https://github.githubassets.com/images/icons/emoji/unicode/1f605.png\">\ud83d\ude05</g-emoji></p>\n<p>\u6771\u5927\u9662\u5352\u306e\u3053\u3044\u3064\u306b\u305b\u3088\u3001 STAP \u306e\u65e9\u7a32\u7530\u5927\u5b66\u9662\u5352\u306b\u305b\u3088\u3001\u3053\u306e\u4e16\u4ee3\u306e\u3053\u3046\u3044\u3046\u5974\u3089\u3068\u304b\u307f\u3066\u308b\u3068\u6697\u6fb9\u305f\u308b\u6c17\u5206\u306b\u306a\u3063\u3066\u304d\u307e\u305b\u3093\u304b\u306d\u3002\u304d\u307e\u305b\u3093\u304b\u3002\u305d\u3046\u3067\u3059\u304b\u3002\u524d\u5411\u304d\u306a\u4eba\u9054\u3067\u3059\u306d\u3002</p>\n</div>","styles":["/css/github-markdown.css","/css/markdown-include.css"],"updated":"2021-07-16T04:14:16","published":"2021-07-16T04:14:16"}