{"title":"2020-02-05","virtualPath":"/Diary/","html":"<p><a href=\"https://www.yamareco.com/10th/?p=6138\" rel=\"nofollow\">yamareco のブログ</a> にコメントを投下してみた。あの投稿は善意で動いてる人に冷や水をぶっかける行為だと思う。</p>\n<hr>\n<p>あの人もすっかり忘れた頃に動きがあるな。</p>\n<p><a href=\"img/2020/2020-02-05/33ca2bf81215a7ada16b18c108dcb29d.png\" target=\"_blank\" rel=\"noopener noreferrer\"><img src=\"img/2020/2020-02-05/33ca2bf81215a7ada16b18c108dcb29d.png\" alt=\"\" style=\"max-width:100%;\"></a>\n<a href=\"img/2020/2020-02-05/14886baea32d6d131f18dcf3f3387c2d.png\" target=\"_blank\" rel=\"noopener noreferrer\"><img src=\"img/2020/2020-02-05/14886baea32d6d131f18dcf3f3387c2d.png\" alt=\"\" style=\"max-width:100%;\"></a></p>\n<p>なーにが XF 窓口だよ。 XF 陰口叩いてるチンピラグループだろ。</p>\n<hr>\n<p><a href=\"http://www5a.biglobe.ne.jp/~mizote/kannri.htm\" rel=\"nofollow\">http://www5a.biglobe.ne.jp/~mizote/kannri.htm</a></p>\n<blockquote>\n<p>自然状態の山岳地帯はもともと所有権の観念に馴染みにくい。土地所有権は土地に資本を投下して管理することから生じたという歴史的経緯があり（注４）、資本投下や管理のされていない砂漠、不毛の山岳地帯、深海の海底、海の岩礁などは、所有権の対象として考えにくい。管理権は所有権から派生する権限であり、管理責任は管理権と密接な関係がある。</p>\n</blockquote>\n<p>やはり、権利、管理が及んでいるか否かというのは重要なポイントだよね。</p>\n<blockquote>\n<p>⑥立山の地獄谷の遊歩道付近の湯だまりで入浴した登山者が有毒ガスを吸引して死亡した事故について、遊歩道の営造物責任を否定。広島高裁平成１１年９月３０日判決（注５）　</p>\n</blockquote>\n<p>これは前に読んだやつやw なお、これで亡くなったのは弁護士。</p>\n<blockquote>\n<p>登山は人間の文化的欲求の表現形式</p>\n</blockquote>\n<p>溝手康史弁護士はこの分野の第一人者のようである。登山をすることに加え、さすが弁護士、ポイントを突いてる。</p>\n<blockquote>\n<p>ヨーロッパでは、歩くかどうかを基準にhiking とclimbingを区分し、岩稜の歩行や、アイゼン、ピッケル、ロープを使用する氷河の歩行はhikingである（日本語のハイキングとは意味が異なる）。</p>\n</blockquote>\n<p>ほーー</p>\n<hr>\n\n\n\n\n\n\n\n\n\n\n\n\n\n\n\n\n\n\n\n\n\n\n\n\n\n\n\n\n\n\n\n\n\n\n\n\n\n\n\n\n\n\n\n\n\n\n\n\n\n\n\n\n\n\n\n<p><a href=\"https://www.yamareco.com/10th/?p=6138\" rel=\"nofollow\">これ</a> 軽く火がつきはじめたかな？炎上ネタは関わりたくないんだけど、このネタは見過ごすのも難しいんだよな。</p>\n<p>昨日の FS おやまもそうだけど、公式アカウントからは誰かを傷つけるリスキーな情報を発するべきではないよなぁ。私的な投稿は、表現の自由で守られるべきだとは思うけどね。</p>\n<hr>\n<p>今日こそ、レイドアワー無理でしょ。</p>\n<p>昨日、イワーク湧いてたの、なんだったんかなーと思ったら酷評されてるねw</p>\n","styles":["/css/github-markdown.css","/css/markdown-include.css"],"description":"日記","updated":"2020-02-07T17:24:05","published":"2020-02-07T17:24:05"}