{"title":"2019-05-17","virtualPath":"/Diary/","html":"<div class=\"markdown-body\"><p><a href=\"https://twitter.com/sinXsan/status/1127965685882036224\" rel=\"nofollow\">https://twitter.com/sinXsan/status/1127965685882036224</a></p>\n<p>こういうさ。背中がぞくぞくする長さで中身のない文章をわざわざ文字起こししてるだけの Portal Description だったら落とした方がいいんじゃない。</p>\n<p>ポータル名もやたら長いので、簡潔に文章を書く能力がすごく低い人じゃないかな。</p>\n<p>すり切れてて読めない、とかならわざわざ書く意味ないだろw</p>\n<hr>\n<p>人に会うかもしれないゲームって言うじゃない。会うかもしれない人はゲーム内のプレイヤに限った話じゃないのよ。大学の先生、学生かもしれない。「一般的」にはアクセスしづらい場所に行く釣り人、登山者かもしれない。</p>\n<p>事あるごとにダメ出ししてよろこんでる人達、その辺りをきっと分かってない。</p>\n<p>都市部や人口の多いエリアで会ったのは Agent が多かった。偶然、出会ったのは緑がほとんど。田舎、僻地で会う Agent はめったにいなくて、地元の人が多いのよ。「何やってんの？」みたいな流れで。ゲームの説明をしたこともあれば、軽く嘘で流したこともある。「お寺/神社の写真撮ってるんですよー。」みたいなね。</p>\n<hr>\n<p><a href=\"https://twitter.com/sinXsan/statuses/1129153806158008320\" rel=\"nofollow\">https://twitter.com/sinXsan/statuses/1129153806158008320</a></p>\n<p>一般的に大学構内は普通に入れるんだけど。この人、わざわざ特定の申請を晒しものにしてるけど、近くにいる人にシバかれたりしないもんですかね。この方、近くにいたら挨拶がわりに小突きまわすなぁw</p>\n<p>位置情報晒すゲームなんかしてて、上から目線のコメント一方的にぶん投げてるけど、シバかれない自信でもなにか持ってるのかしらん。</p>\n<p>昨日も書いたけど、ご本人が失礼なことまったく自覚してないので、その内ゴミの様に路傍に打ち棄てられていそう。</p>\n</div>","styles":["/css/github-markdown.css","/css/markdown-include.css"],"description":"日記,つぶやき,雑記帳","updated":"2019-09-27T08:33:24","published":"2019-09-27T08:33:24"}