{"title":"2021-06-01","virtualPath":"/Diary/","anchorId":"Kj9ps1HRr4","anchorLink":"/Gitwee/timeline/2021/06/01","description":"\u65e5\u8a18,\u3064\u3076\u3084\u304d,\u96d1\u8a18\u5e33,\u6642\u4e8b,\u5b9d\u9054\u5c71","tags":[{"title":"\u6642\u4e8b","tagkey":"inkM5pkcdzCmwgjjDE5G-A","link":"/Gitwee/tag/inkM5pkcdzCmwgjjDE5G-A"},{"title":"\u5b9d\u9054\u5c71","tagkey":"vmhNSat8bVvDo_pzh6IBow","link":"/Gitwee/tag/vmhNSat8bVvDo_pzh6IBow"}],"html":"<div class=\"markdown-body\"><p><em>06/01 \u5317\u570b\u65b0\u805e\u671d\u520a\u3088\u308a\u5f15\u7528</em></p>\n\n<p><a href=\"/MyContents2021/2021-06-01/Kj9ps1HRr40VvzFK/20210601-173810-P_20210601_173810_vHDR_Auto.jpg\" target=\"_blank\" rel=\"noopener noreferrer\"><img src=\"/MyContents2021/2021-06-01/Kj9ps1HRr40VvzFK/20210601-173810-P_20210601_173810_vHDR_Auto.jpg\" alt=\"myimage://2021/2021-06-01/Kj9ps1HRr40VvzFK/20210601-173810-P_20210601_173810_vHDR_Auto.large.jpg\" style=\"max-width:100%;\"></a></p>\n<p>\u30c8\u30a4\u30ec\u6383\u9664\u3059\u3089\u5584\u610f\u306b\u983c\u3063\u3066\u3044\u308b\u306e\u306b\u3001\u306a\u3093\u3067\u65b0\u305f\u306a\u65bd\u8a2d\u304c\u958b\u3051\u308b\u3068\u601d\u3046\u306e\u3084\u3089\u3002</p>\n</div>","styles":["/css/github-markdown.css","/css/markdown-include.css"],"updated":"2022-04-29T03:51:55","published":"2021-11-02T08:04:49","updatedAt":"2022-04-28T18:51:55.00Z","publishedAt":"2021-11-01T23:04:49.00Z"}