{"title":"2023-04-17","virtualPath":"/Diary/","anchorId":"9C7n9RQ8ch","anchorLink":"/Gitwee/timeline/2023/04/17","description":"\u65e5\u8a18,\u3064\u3076\u3084\u304d,\u96d1\u8a18\u5e33,\u30a2\u30cb\u30e1,\u6c34\u661f\u306e\u9b54\u5973","tags":[{"title":"\u30a2\u30cb\u30e1","tagkey":"wK86EmRL-NRk_Sz8POYSXQ","link":"/Gitwee/tag/wK86EmRL-NRk_Sz8POYSXQ"},{"title":"\u6c34\u661f\u306e\u9b54\u5973","tagkey":"bE0WpD3IjHKd4TRs9Rgmzw","link":"/Gitwee/tag/bE0WpD3IjHKd4TRs9Rgmzw"}],"html":"<div class=\"markdown-body\"><p>\u3053\u308c\u3082\u6d41\u884c\u308a\u3082\u306e\u306a\u306e\u3067\u306a\u3093\u3068\u304b\u5f53\u65e5\u4e2d\u306b\u89b3\u7d42\u308f\u3063\u305f\u3002</p>\n<p>\u3053\u306e\u56de\u3067\u3088\u3046\u3084\u304f\u6838\u5fc3\u90e8\u5206\u306b\u89e6\u308c\u305f\u3093\u3060\u308d\u3046\u304b\u3002\u30a8\u30ea\u30af\u30c8\u304c\u30ac\u30f3\u30c0\u30e0\u30a8\u30a2\u30ea\u30a2\u30eb\u306e\u4e2d\u306b\u3044\u308b\u3001\u3068\u3002quiet zero\u3001\u3068\u306f\uff1f</p>\n\n<p><a target=\"_blank\" rel=\"noopener noreferrer\" href=\"/MyContents2023/2023-04-17/9C7n9RQ8ch_uR_Fq/dbaf8ac3e501c8ab47ab374a593c7406.jpg\"><img src=\"/MyContents2023/2023-04-17/9C7n9RQ8ch_uR_Fq/dbaf8ac3e501c8ab47ab374a593c7406.jpg\" alt=\"\" style=\"max-width: 100%;\"></a></p>\n<p>\u30ad\u30e3\u30e9\u304c\u3044\u3063\u3071\u3044\u51fa\u3059\u304e\u3066\u3066\u3001\u4ffa\u306b\u306f\u3088\u304f\u5206\u304b\u3089\u3093\u3002</p>\n\n<p><a target=\"_blank\" rel=\"noopener noreferrer\" href=\"/MyContents2023/2023-04-17/9C7n9RQ8ch_uR_Fq/4ca7953c68e57ed689d8aedc75f6283d.jpg\"><img src=\"/MyContents2023/2023-04-17/9C7n9RQ8ch_uR_Fq/4ca7953c68e57ed689d8aedc75f6283d.jpg\" alt=\"\" style=\"max-width: 100%;\"></a></p>\n</div>","styles":["/css/github-markdown.css","/css/markdown-include.css"],"updated":"2023-06-23T04:08:58","published":"2023-04-18T02:58:57","updatedAt":"2023-06-22T19:08:58.00Z","publishedAt":"2023-04-17T17:58:57.00Z"}