{"title":"2026-05-06","virtualPath":"/Diary/","anchorId":"HHYPgwRPsv","anchorLink":"/Gitwee/timeline/2026/05/06","description":"\u65e5\u8a18,\u3064\u3076\u3084\u304d,\u96d1\u8a18\u5e33,\u6599\u7406","tags":[{"title":"\u6599\u7406","tagkey":"jlRf-uUVG7NW2IUplSvLTQ","link":"/Gitwee/tag/jlRf-uUVG7NW2IUplSvLTQ"}],"html":"<div class=\"markdown-body\"><p>\u4e45\u3005\u306e\u89aa\u5b50\u4e3c\u3068\u3044\u305f\u3057\u307e\u3057\u3087\u3046\u3002</p>\n\n<p><a target=\"_blank\" rel=\"noopener noreferrer\" href=\"/MyContents2026/2026-05-06/HHYPgwRPsvVJb35L/2d04720ac9d3c4f5673b20493bc13ce5.jpg\"><img src=\"/MyContents2026/2026-05-06/HHYPgwRPsvVJb35L/2d04720ac9d3c4f5673b20493bc13ce5.jpg\" alt=\"\" style=\"max-width: 100%;\"></a></p>\n</div>","styles":["/css/github-markdown.css","/css/markdown-include.css"],"updated":"2026-05-07T22:31:42","published":"2026-05-07T22:31:42","updatedAt":"2026-05-07T13:31:42.00Z","publishedAt":"2026-05-07T13:31:42.00Z"}