{"title":"2022-07-06","virtualPath":"/Diary/","anchorId":"26chd8uUey","anchorLink":"/Gitwee/timeline/2022/07/06","description":"\u65e5\u8a18,\u3064\u3076\u3084\u304d,\u96d1\u8a18\u5e33,\u30dd\u30b1\u30e2\u30f3go","tags":[{"title":"\u30dd\u30b1\u30e2\u30f3go","tagkey":"lxfDm7aaLlErPTsvONpziw","link":"/Gitwee/tag/lxfDm7aaLlErPTsvONpziw"}],"html":"<div class=\"markdown-body\"><p>\u307e\u305f\u3072\u3067\u3047\u30b4\u30df\u3092\u58f2\u3063\u3066\u308b\u3002\u3068\u3046\u3068\u3046\u307b\u3093\u3068\u306b\u30a4\u30ab\u308c\u305f\u306e\u304b\u3002</p>\n\n<p><a href=\"/MyContents2022/2022-07-06/26chd8uUeykcxvIr/20220706-182833-Screenshot_20220706-182833427.jpg\" target=\"_blank\" rel=\"noopener noreferrer\"><img src=\"/MyContents2022/2022-07-06/26chd8uUeykcxvIr/20220706-182833-Screenshot_20220706-182833427.jpg\" alt=\"\" style=\"max-width:100%;\"></a></p>\n</div>","styles":["/css/github-markdown.css","/css/markdown-include.css"],"updated":"2022-07-06T16:03:59","published":"2022-07-06T16:03:59","updatedAt":"2022-07-06T07:03:59.00Z","publishedAt":"2022-07-06T07:03:59.00Z"}