{"title":"2024-01-09","virtualPath":"/Diary/","anchorId":"pwTBg1Vwnk","anchorLink":"/Gitwee/timeline/2024/01/09","description":"\u65e5\u8a18,\u3064\u3076\u3084\u304d,\u96d1\u8a18\u5e33,\u30e2\u30f3\u30cf\u30f3Now","tags":[{"title":"\u30e2\u30f3\u30cf\u30f3Now","tagkey":"Ga9v46pU3Ch7xz2sKLEMdA","link":"/Gitwee/tag/Ga9v46pU3Ch7xz2sKLEMdA"}],"html":"<div class=\"markdown-body\"><p>\u30b8\u30f3\u30aa\u30a6\u30ac \u2b50 5 \u8a0e\u4f10\u6210\u529f</p>\n\n\n<p><a target=\"_blank\" rel=\"noopener noreferrer\" href=\"/MyContents2024/2024-01-09/pwTBg1VwnkAsF0md/20240108-183501-Screenshot_20240108-183501.jpg\"><img src=\"/MyContents2024/2024-01-09/pwTBg1VwnkAsF0md/20240108-183501-Screenshot_20240108-183501.jpg\" alt=\"\" style=\"max-width: 100%;\"></a>\n<a target=\"_blank\" rel=\"noopener noreferrer\" href=\"/MyContents2024/2024-01-09/pwTBg1VwnkAsF0md/20240108-183505-Screenshot_20240108-183505.jpg\"><img src=\"/MyContents2024/2024-01-09/pwTBg1VwnkAsF0md/20240108-183505-Screenshot_20240108-183505.jpg\" alt=\"\" style=\"max-width: 100%;\"></a></p>\n<p>rare 3 \u306e\u65b9\u304c\u3067\u3065\u3089\u3044\u3001\u306e\u304b\uff1f\u3053\u308c\u306f\u3069\u3063\u304b\u7279\u5b9a\u306e\u90e8\u4f4d\u7834\u58ca\u3092\u3057\u306a\u3044\u3068\u3044\u3051\u306a\u3044\u306e\u3060\u308d\u3046\u304b\u3002</p>\n\n<p><a target=\"_blank\" rel=\"noopener noreferrer\" href=\"/MyContents2024/2024-01-09/pwTBg1VwnkAsF0md/20240108-183515-Screenshot_20240108-183515.jpg\"><img src=\"/MyContents2024/2024-01-09/pwTBg1VwnkAsF0md/20240108-183515-Screenshot_20240108-183515.jpg\" alt=\"\" style=\"max-width: 100%;\"></a></p>\n<p>\u3042\u308b\u3044\u306f\u4f55\u304b\u306e\u5831\u916c\u3067\u51fa\u305f\u306e\u304b\u2026 \u65e9\u304f\u3064\u304f\u308a\u305f\u3044\u3002</p>\n</div>","styles":["/css/github-markdown.css","/css/markdown-include.css"],"updated":"2024-01-09T06:48:03","published":"2024-01-09T06:48:03","updatedAt":"2024-01-08T21:48:03.00Z","publishedAt":"2024-01-08T21:48:03.00Z"}