{"virtualPath":"/Diary/essay/2025/","anchorLink":"/Diary/essay/2025/2025-10-21.htm","hasMain":true,"description":"\u65e5\u8a18,\u968f\u7b46,\u7c21\u7d04\u7248,\u767b\u5c71,\u98df\u4e8b,\u7d05\u8449,\u98db\u9a28,\u5c90\u961c,\u98db\u9a28\u9ad8\u5c71","title":"2025-10-21 \u91ce\u8c37\u8358\u53f8\u5c71 - \u4e09\u65b9\u5ca9\u5cb3 - \u98db\u9a28\u9ad8\u5c71","tags":[{"title":"\u767b\u5c71","tagkey":"hDV03PuC-3z2fJG0rlOhSA","link":"/Gitwee/tag/hDV03PuC-3z2fJG0rlOhSA"},{"title":"\u98df\u4e8b","tagkey":"BK4GxVND6VDHvfHP_-FQlQ","link":"/Gitwee/tag/BK4GxVND6VDHvfHP_-FQlQ"},{"title":"\u7d05\u8449","tagkey":"2-ZLcTJsOe3t9D2vu5IQmQ","link":"/Gitwee/tag/2-ZLcTJsOe3t9D2vu5IQmQ"},{"title":"\u98db\u9a28","tagkey":"j9B0MX1CRmiSeae5tPy6iw","link":"/Gitwee/tag/j9B0MX1CRmiSeae5tPy6iw"},{"title":"\u5c90\u961c","tagkey":"H7Tegf7Rq0NcOEa_S_cO9w","link":"/Gitwee/tag/H7Tegf7Rq0NcOEa_S_cO9w"},{"title":"\u98db\u9a28\u9ad8\u5c71","tagkey":"IYqYa2dn_toSM5qnTd0sSg","link":"/Gitwee/tag/IYqYa2dn_toSM5qnTd0sSg"}],"html":"<div class=\"markdown-body\"><p>\u98db\u9a28\u3078\u306e\u9060\u5f81\u3067\u3001\u6570\u5e74\u3076\u308a\u306b\u91ce\u8c37\u8358\u53f8\u5c71\u3078\u3002\u8ddd\u96e2 15km \u7372\u5f97\u6a19\u9ad8\u7d04 1550m</p>\n<p><iframe src=\"https://www.yamareco.com/modules/yamareco/include/ymap_iframe.php?did=8870920&graph=1&w=480&h=320&lat=36.2548765&lon=136.859977&minlat=36.245824&minlon=136.837079&maxlat=36.263929&maxlon=136.882875\" width=\"100%\" height=\"502\" scrolling=\"no\" frameborder=\"0\"></iframe>\n</p>\n<div class=\"markdown-heading\"><h2 class=\"heading-element\">\u91ce\u8c37\u8358\u53f8\u5c71 - \u4e09\u65b9\u5ca9\u5cb3</h2><a id=\"user-content-\u91ce\u8c37\u8358\u53f8\u5c71---\u4e09\u65b9\u5ca9\u5cb3\" class=\"anchor\" aria-label=\"Permalink: \u91ce\u8c37\u8358\u53f8\u5c71 - \u4e09\u65b9\u5ca9\u5cb3\" href=\"#\u91ce\u8c37\u8358\u53f8\u5c71---\u4e09\u65b9\u5ca9\u5cb3\"><span aria-hidden=\"true\" class=\"octicon octicon-link\"></span></a></div>\n<p>\u733f\u306e\u3053\u3057\u304b\u3051</p>\n\n<p><a target=\"_blank\" rel=\"noopener noreferrer\" href=\"/MyContents2025/2025-10-21/xW3hjMBIiwTHOJhq/20251021-071026-IMG_20251021_071024189_HDR.jpg\"><img src=\"/MyContents2025/2025-10-21/xW3hjMBIiwTHOJhq/20251021-071026-IMG_20251021_071024189_HDR.jpg\" alt=\"\" style=\"max-width: 100%;\"></a></p>\n</div>","styles":["/css/github-markdown.css","/css/markdown-include.css"],"updated":"2025-10-29T12:25:08","published":"2025-10-24T11:58:21","updatedAt":"2025-10-29T03:25:08.00Z","publishedAt":"2025-10-24T02:58:21.00Z"}