{"title":"2021-11-15","virtualPath":"/Diary/","anchorId":"g5PYTvkeDa","anchorLink":"/Gitwee/timeline/2021/11/15","description":"\u65e5\u8a18,\u3064\u3076\u3084\u304d,\u96d1\u8a18\u5e33","tags":[{"title":"\u30dd\u30b1\u30e2\u30f3go","tagkey":"lxfDm7aaLlErPTsvONpziw","link":"/Gitwee/tag/lxfDm7aaLlErPTsvONpziw"}],"html":"<div class=\"markdown-body\"><p>\u5148\u9031\u306f\u3084\u3063\u3068\u306e 26km</p>\n\n<p><a href=\"/MyContents2021/2021-11-15/g5PYTvkeDa2mfBUf/20211115-091613-Screenshot_20211115-091613541.jpg\" target=\"_blank\" rel=\"noopener noreferrer\"><img src=\"/MyContents2021/2021-11-15/g5PYTvkeDa2mfBUf/20211115-091613-Screenshot_20211115-091613541.jpg\" alt=\"\" style=\"max-width:100%;\"></a></p>\n</div>","styles":["/css/github-markdown.css","/css/markdown-include.css"],"updated":"2021-11-15T02:11:48","published":"2021-11-15T02:11:48"}