{"title":"2022-07-07","virtualPath":"/Diary/","anchorId":"YNjdyyhUHt","anchorLink":"/Gitwee/timeline/2022/07/07","description":"\u65e5\u8a18,\u3064\u3076\u3084\u304d,\u96d1\u8a18\u5e33,Web,\u6642\u4e8b","tags":[{"title":"Web","tagkey":"xuGQsoRjPEjjnlUEnaPM6A","link":"/Gitwee/tag/xuGQsoRjPEjjnlUEnaPM6A"},{"title":"\u6642\u4e8b","tagkey":"inkM5pkcdzCmwgjjDE5G-A","link":"/Gitwee/tag/inkM5pkcdzCmwgjjDE5G-A"}],"html":"<div class=\"markdown-body\"><p>\u5c71\u7530\u592a\u90ce\u3001\u5c71\u672c\u4e00\u90ce\u3001\u5c71\u672c\u592a\u90ce\u3001\u3060\u3063\u3051\u3002 <g-emoji class=\"g-emoji\" alias=\"sweat_smile\" fallback-src=\"https://github.githubassets.com/images/icons/emoji/unicode/1f605.png\">\ud83d\ude05</g-emoji> \u899a\u3048\u3089\u308c\u306d\u3047\u2026</p>\n</div>","styles":["/css/github-markdown.css","/css/markdown-include.css"],"updated":"2022-07-08T07:27:35","published":"2022-07-08T07:27:35","updatedAt":"2022-07-07T22:27:35.00Z","publishedAt":"2022-07-07T22:27:35.00Z"}