{"title":"2022-10-03","virtualPath":"/Diary/","anchorId":"tJ93r98ETV","anchorLink":"/Gitwee/timeline/2022/10/03","description":"\u65e5\u8a18,\u3064\u3076\u3084\u304d,\u96d1\u8a18\u5e33,\u30dd\u30b1\u30e2\u30f3go","tags":[{"title":"\u30dd\u30b1\u30e2\u30f3go","tagkey":"lxfDm7aaLlErPTsvONpziw","link":"/Gitwee/tag/lxfDm7aaLlErPTsvONpziw"}],"html":"<div class=\"markdown-body\"><p>\u3084\u3063\u3068\u3001\u304d\u305f\u3002\u30d5\u30a7\u30a2\u30ea\u30fc\u30bf\u30a4\u30d7\u306e\u30a2\u30bf\u30c3\u30ab\u30fc\u306b\u306a\u308b\u3002</p>\n\n<p><a target=\"_blank\" rel=\"noopener noreferrer\" href=\"/MyContents2022/2022-10-03/tJ93r98ETVz50GRm/20221002-231734-Screenshot_20221002-231734812.jpg\"><img src=\"/MyContents2022/2022-10-03/tJ93r98ETVz50GRm/20221002-231734-Screenshot_20221002-231734812.jpg\" alt=\"\" style=\"max-width: 100%;\"></a></p>\n</div>","styles":["/css/github-markdown.css","/css/markdown-include.css"],"updated":"2022-10-04T04:32:52","published":"2022-10-04T04:32:52","updatedAt":"2022-10-03T19:32:52.00Z","publishedAt":"2022-10-03T19:32:52.00Z"}